pixa/__init__.py
pixa/__main__.py
pixa/client.py
pixa/clip.py
pixa/consts.py
pixa/server.py
pixa/storage.py
pixa/utils.py
pixa-0.1.0.dist-info/WHEEL
pixa-0.1.0.dist-info/entry_points.txt
pixa-0.1.0.dist-info/METADATA
pixa-0.1.0.dist-info/RECORD
