Metadata-Version: 2.3
Name: pixa
Version: 0.1.0
Summary: Image finder for searching images by image.
Author: Seamile
Author-email: Seamile <lanhuermao@gmail.com>
Requires-Dist: torch==2.2.2 ; platform_machine == 'x86_64' and sys_platform == 'darwin'
Requires-Dist: torch>=2.8.0 ; platform_machine != 'x86_64' or sys_platform != 'darwin'
Requires-Dist: torchvision>=0.17.2
Requires-Dist: numpy<2 ; platform_machine == 'x86_64' and sys_platform == 'darwin'
Requires-Dist: numpy>=1.24.0 ; platform_machine != 'x86_64' or sys_platform != 'darwin'
Requires-Dist: bidict>=0.23.1
Requires-Dist: hnswlib>=0.8.0
Requires-Dist: msgpack>=1.1.1
Requires-Dist: pillow>=11.3.0
Requires-Dist: pyro5>=5.15
Requires-Dist: transformers>=4.55.4
Requires-Python: >=3.11
